AUTHORS
ChangeLog
LICENSE
MANIFEST.in
Makefile
README.rst
doc_requirements.txt
example.py
requirements.txt
rest_example.py
setup.cfg
setup.py
test_requirements.txt
unittests.py
pygerrit/__init__.py
pygerrit/client.py
pygerrit/error.py
pygerrit/events.py
pygerrit/models.py
pygerrit/ssh.py
pygerrit/stream.py
pygerrit.egg-info/PKG-INFO
pygerrit.egg-info/SOURCES.txt
pygerrit.egg-info/dependency_links.txt
pygerrit.egg-info/not-zip-safe
pygerrit.egg-info/pbr.json
pygerrit.egg-info/requires.txt
pygerrit.egg-info/top_level.txt
pygerrit/rest/__init__.py
pygerrit/rest/auth.py
testdata/change-abandoned-event.txt
testdata/change-merged-event.txt
testdata/change-restored-event.txt
testdata/comment-added-event.txt
testdata/draft-published-event.txt
testdata/invalid-json.txt
testdata/merge-failed-event.txt
testdata/patchset-created-event.txt
testdata/ref-updated-event.txt
testdata/reviewer-added-event.txt
testdata/topic-changed-event.txt
testdata/unhandled-event.txt
testdata/user-defined-event.txt