Metadata-Version: 1.0
Name: pygerrit
Version: 1.0.0
Summary: Client library for interacting with Gerrit
Home-page: https://github.com/sonyxperiadev/pygerrit
Author: David Pursehouse
Author-email: david.pursehouse@sonymobile.com
License: The MIT License
Keywords: gerrit
Platform: UNKNOWN
